fudge/__init__.py
fudge/exc.py
fudge/inspector.py
fudge/patcher.py
fudge/util.py
fudge/tests/__init__.py
fudge/tests/_for_patch.py
fudge/tests/test_fudge.py
fudge/tests/test_inspector.py
fudge/tests/test_patcher.py
fudge/tests/test_registry.py
fudgy-1.1.1.dist-info/licenses/LICENSE
fudgy-1.1.1.dist-info/WHEEL
fudgy-1.1.1.dist-info/METADATA
fudgy-1.1.1.dist-info/RECORD
