Metadata-Version: 2.4
Name: fudgy
Version: 1.1.1
Summary: Replace real objects with fakes for testing purposes
Keywords: fake,fudge,mock,stub
Author-email: Anton Zhiyanov <m@antonz.org>
Requires-Python: >=3.9
Classifier: License :: OSI Approved :: MIT License
Classifier: Programming Language :: Python :: 3
License-File: LICENSE
Project-URL: Source, https://github.com/nalgeon/fudgy
